pylisa.cp39-win_amd64.pyd
pylisa-0.0.1.dist-info/LICENSE.md
pylisa-0.0.1.dist-info/METADATA
pylisa-0.0.1.dist-info/WHEEL
pylisa-0.0.1.dist-info/top_level.txt
pylisa-0.0.1.dist-info/RECORD
